LICENSE
README.rst
setup.py
pltx/__init__.py
pltx/_tools.py
pltx.egg-info/PKG-INFO
pltx.egg-info/SOURCES.txt
pltx.egg-info/dependency_links.txt
pltx.egg-info/not-zip-safe
pltx.egg-info/requires.txt
pltx.egg-info/top_level.txt