Metadata-Version: 2.1
Name: pltx
Version: 0.2.5
Summary: Tools of matplotlib
Home-page: https://gitee.com/summry/pltx
Author: summy
Author-email: fkfkfk2024@2925.com
License: UNKNOWN
Keywords: matplotlib
Platform: UNKNOWN
Requires-Python: >=3.6
License-File: LICENSE
